icarus_nmr/__init__.py
icarus_nmr/_version.py
icarus_nmr/analysis.py
icarus_nmr/device_daq.py
icarus_nmr/device_server.py
icarus_nmr/dio_client.py
icarus_nmr/dio_handler.py
icarus_nmr/dio_server.py
icarus_nmr/driver_mock.py
icarus_nmr/driver_usb_bulk_di_4108.py
icarus_nmr/event_client.py
icarus_nmr/event_daq.py
icarus_nmr/event_handler.py
icarus_nmr/event_server.py
icarus_nmr/logging_client.py
icarus_nmr/logging_logging.py
icarus_nmr/pyepics.py
icarus_nmr/tests/__init__.py
icarus_nmr/tests/conftest.py
icarus_nmr/tests/test_analysis.py
icarus_nmr/tests/test_examples.py
icarus_nmr/tests/test_mock_device.py
icarus_nmr/tests/test_mock_driver.py
icarus_nmr/tests/test_data/__init__.py
icarus_nmr/tests/test_data/mock_driver/__init__.py
icarus_nmr/tests/test_data/mock_driver/traces.py
icarus_nmr-0.1.0.dist-info/AUTHORS.rst
icarus_nmr-0.1.0.dist-info/LICENSE
icarus_nmr-0.1.0.dist-info/METADATA
icarus_nmr-0.1.0.dist-info/WHEEL
icarus_nmr-0.1.0.dist-info/entry_points.txt
icarus_nmr-0.1.0.dist-info/top_level.txt
icarus_nmr-0.1.0.dist-info/RECORD
